climeval/__init__.py
climeval/cli.py
climeval/core.py
climeval/dask_setup.py
climeval/utils.py
climeval/visualization.py
climeval-0.1.1.dist-info/LICENSE
climeval-0.1.1.dist-info/METADATA
climeval-0.1.1.dist-info/WHEEL
climeval-0.1.1.dist-info/entry_points.txt
climeval-0.1.1.dist-info/top_level.txt
climeval-0.1.1.dist-info/RECORD
