Metadata-Version: 2.2
Name: climeval
Version: 0.1.1
Summary: Climate Model vs. Observation Comparison Tool
Home-page: https://github.com/shiv3679/ClimEval
Author: Shiv Shankar Singh
Author-email: Shiv Shankar Singh <shivshankarsingh.py@gmail.com>
License: MIT
Project-URL: Homepage, https://github.com/shiv3679/ClimEval
Project-URL: Bug Tracker, https://github.com/shiv3679/ClimEval/issues
Keywords: climate,verification,model,evaluation,dask
Classifier: Development Status :: 3 - Alpha
Classifier: Intended Audience :: Science/Research
Classifier: License :: OSI Approved :: MIT License
Classifier: Programming Language :: Python :: 3
Classifier: Programming Language :: Python :: 3.7
Classifier: Programming Language :: Python :: 3.8
Classifier: Programming Language :: Python :: 3.9
Classifier: Programming Language :: Python :: 3.10
Requires-Python: >=3.7
License-File: LICENSE
Requires-Dist: numpy
Requires-Dist: xarray
Requires-Dist: dask
Requires-Dist: scipy
Requires-Dist: matplotlib
Requires-Dist: cartopy
Requires-Dist: pytest
Dynamic: author
Dynamic: home-page
Dynamic: requires-python
